{
    "title": "Car Models Collection",
    "version": "1.0",
    "href": "https://example.com/car-models",
    "results": [
        {
            "title": "Toyota Corolla",
            "href": "https://example.com/car-models/toyota-corolla",
            "description": "The Toyota Corolla is a compact car that has been popular for decades due to its reliability and fuel efficiency.",
            "thumbnail": "https://example.com/thumbnails/toyota-corolla.jpg"
        },
        {
            "title": "Tesla Model S",
            "href": "https://example.com/car-models/tesla-model-s",
            "description": "The Tesla Model S is an all-electric luxury sedan known for its groundbreaking technology and impressive performance.",
            "thumbnail": "https://example.com/thumbnails/tesla-model-s.jpg"
        },
        {
            "title": "Ford F-150",
            "href": "https://example.com/car-models/ford-f150",
            "description": "The Ford F-150 is a full-size pickup truck that is consistently one of the best-selling vehicles in the United States.",
            "thumbnail": "https://example.com/thumbnails/ford-f150.jpg"
        },
        {
            "title": "Honda Civic",
            "href": "https://example.com/car-models/honda-civic",
            "description": "The Honda Civic is a popular compact car known for its reliability, fuel efficiency, and sporty design.",
            "thumbnail": "https://example.com/thumbnails/honda-civic.jpg"
        },
        {
            "title": "Chevrolet Camaro",
            "href": "https://example.com/car-models/chevrolet-camaro",
            "description": "The Chevrolet Camaro is a classic American muscle car known for its powerful performance and iconic design.",
            "thumbnail": "https://example.com/thumbnails/chevrolet-camaro.jpg"
        },
        {
            "title": "Jeep Wrangler",
            "href": "https://example.com/car-models/jeep-wrangler",
            "description": "The Jeep Wrangler is a rugged SUV known for its off-road capability and iconic design.",
            "thumbnail": "https://example.com/thumbnails/jeep-wrangler.jpg"
        },
        {
            "title": "BMW 3 Series",
            "href": "https://example.com/car-models/bmw-3-series",
            "description": "The BMW 3 Series is a luxury compact car known for its sporty handling and upscale interior.",
            "thumbnail": "https://example.com/thumbnails/bmw-3-series.jpg"
        },
        {
            "title": "Mercedes-Benz E-Class",
            "href": "https://example.com/car-models/mercedes-e-class",
            "description": "The Mercedes-Benz E-Class is a luxury midsize car known for its refined interior, advanced technology, and comfortable ride.",
            "thumbnail": "https://example.com/thumbnails/mercedes-e-class.jpg"
        },
        {
            "title": "Audi Q5",
            "href": "https://example.com/car-models/audi-q5",
            "description": "The Audi Q5 is a luxury compact SUV known for its elegant design, upscale interior, and strong performance.",
            "thumbnail": "https://example.com/thumbnails/audi-q5.jpg"
        }
    ]
}
